mosaik_components/wind/Simulator.py
mosaik_components/wind/WindTurbine.py
mosaik_components/wind/__init__.py
mosaik_wind-0.2.0.dist-info/AUTHORS.txt
mosaik_wind-0.2.0.dist-info/LICENSE
mosaik_wind-0.2.0.dist-info/METADATA
mosaik_wind-0.2.0.dist-info/WHEEL
mosaik_wind-0.2.0.dist-info/RECORD
