Metadata-Version: 2.3
Name: mosaik-wind
Version: 0.2.0
Summary: mosaik simulator for Wind turbine
License: LICENSE
Author: Malte Trauernicht
Author-email: mosaik@offis.de
Requires-Python: >=3.9,<4.0
Classifier: License :: Other/Proprietary License
Classifier: Programming Language :: Python :: 3
Classifier: Programming Language :: Python :: 3.9
Classifier: Programming Language :: Python :: 3.10
Classifier: Programming Language :: Python :: 3.11
Classifier: Programming Language :: Python :: 3.12
Classifier: Programming Language :: Python :: 3.13
Requires-Dist: arrow (>=1.3.0,<2.0.0)
Requires-Dist: mosaik-api-v3 (>=3.0.7,<4.0.0)
Requires-Dist: numpy (>=1.25.2,<2.0.0)
Requires-Dist: pandas (>=2.1.0,<3.0.0)
